IosAnquanWikiFix1/README.md
IosAnquanWikiFix1/__init__.py
IosAnquanWikiFix1/__main__.py
IosAnquanWikiFix1/file.epub
IosAnquanWikiFix1/index.html
IosAnquanWikiFix1/css/__init__.py
IosAnquanWikiFix1/css/annotations.css
IosAnquanWikiFix1/css/main.css
IosAnquanWikiFix1/css/normalize.css
IosAnquanWikiFix1/css/popup.css
IosAnquanWikiFix1/font/__init__.py
IosAnquanWikiFix1/font/fontello.eot
IosAnquanWikiFix1/font/fontello.svg
IosAnquanWikiFix1/font/fontello.ttf
IosAnquanWikiFix1/font/fontello.woff
IosAnquanWikiFix1/img/__init__.py
IosAnquanWikiFix1/img/annotator-glyph-sprite.png
IosAnquanWikiFix1/img/annotator-icon-sprite.png
IosAnquanWikiFix1/img/apple-touch-icon.png
IosAnquanWikiFix1/img/cancelfullscreen.png
IosAnquanWikiFix1/img/close.png
IosAnquanWikiFix1/img/fullscreen.png
IosAnquanWikiFix1/img/loader.gif
IosAnquanWikiFix1/img/menu-icon.png
IosAnquanWikiFix1/img/save.png
IosAnquanWikiFix1/img/saved.png
IosAnquanWikiFix1/img/settings-s.png
IosAnquanWikiFix1/img/settings.png
IosAnquanWikiFix1/img/star.png
IosAnquanWikiFix1/js/__init__.py
IosAnquanWikiFix1/js/epub.js
IosAnquanWikiFix1/js/epub.min.js
IosAnquanWikiFix1/js/epub.min.map
IosAnquanWikiFix1/js/hooks.min.js
IosAnquanWikiFix1/js/hooks.min.map
IosAnquanWikiFix1/js/reader.js
IosAnquanWikiFix1/js/reader.js.map
IosAnquanWikiFix1/js/reader.min.js
IosAnquanWikiFix1/js/reader.min.map
IosAnquanWikiFix1/js/hooks/__init__.py
IosAnquanWikiFix1/js/hooks/extensions/__init__.py
IosAnquanWikiFix1/js/hooks/extensions/highlight.js
IosAnquanWikiFix1/js/libs/__init__.py
IosAnquanWikiFix1/js/libs/jquery.min.js
IosAnquanWikiFix1/js/libs/localforage.min.js
IosAnquanWikiFix1/js/libs/screenfull.js
IosAnquanWikiFix1/js/libs/screenfull.min.js
IosAnquanWikiFix1/js/libs/zip.min.js
IosAnquanWikiFix1/js/plugins/__init__.py
IosAnquanWikiFix1/js/plugins/hypothesis.js
IosAnquanWikiFix1/js/plugins/search.js
ios_anquan_wiki_fix1-2024.3.1.0.dist-info/METADATA
ios_anquan_wiki_fix1-2024.3.1.0.dist-info/WHEEL
ios_anquan_wiki_fix1-2024.3.1.0.dist-info/entry_points.txt
ios_anquan_wiki_fix1-2024.3.1.0.dist-info/top_level.txt
ios_anquan_wiki_fix1-2024.3.1.0.dist-info/RECORD
